decorators/__init__.py
decorators/async_safe.py
decorators/benchmark.py
decorators/cache_decorator.py
decorators/deprecated.py
decorators/logging_decorator.py
decorators/memoize.py
decorators/once.py
decorators/rate_limiter.py
decorators/retry_decorator.py
decorators/suppress_exceptions.py
decorators/time_decorator.py
decorators/validate_types.py
generators/__init__.py
generators/batched_iterable.py
generators/csv_row_reader.py
generators/directory_watcher.py
generators/fibonacci.py
generators/file_chunker.py
generators/paginated_api_reader.py
generators/sliding_window.py
generators/tail_reader.py
pydecorx-1.0.1.dist-info/licenses/LICENSE
pydecorx-1.0.1.dist-info/METADATA
pydecorx-1.0.1.dist-info/WHEEL
pydecorx-1.0.1.dist-info/top_level.txt
pydecorx-1.0.1.dist-info/RECORD
