Metadata-Version: 2.4
Name: pydecorx
Version: 1.0.1
Summary: A collection of production-ready Python decorators and generators
Author-email: Manas Shinde <manas.a.shinde11@example.com>
License: MIT
Project-URL: Homepage, https://github.com/manas-shinde/python-decorators-generators
Keywords: python,decorators,generators,utils
Requires-Python: >=3.8
License-File: LICENSE
Dynamic: license-file
